hl7validator/__init__.py
hl7validator/cli.py
hl7validator/context.py
hl7validator/exceptions.py
hl7validator/mixins.py
hl7validator/operators.py
hl7validator/parser.py
hl7validator/predicates.py
hl7validator/rules.py
hl7validator/selectors.py
hl7validator/transformer.py
hl7validator/validator.py
hl7validator/values.py
hl7validator/resources/base_hl7.rules
hl7validator/resources/hl7validation.lark
hl7_validator-0.3.3.dist-info/LICENSE
hl7_validator-0.3.3.dist-info/METADATA
hl7_validator-0.3.3.dist-info/WHEEL
hl7_validator-0.3.3.dist-info/entry_points.txt
hl7_validator-0.3.3.dist-info/top_level.txt
hl7_validator-0.3.3.dist-info/RECORD
