Metadata-Version: 2.1
Name: hl7-validator
Version: 0.3.3
Summary: HL7 validation helper
Author: Cezary Statkiewicz
Author-email: c.statkiewicz@gmail.com, cezio@thelirium.net
License: MIT
Requires-Python: >=3.7
License-File: LICENSE
Requires-Dist: attrs
Requires-Dist: hl7
Requires-Dist: lark
Requires-Dist: click
